only_utils/__init__.py
only_utils/utils/__init__.py
only_utils/utils/classes.py
tests/__init__.py
tests/utils/__init__.py
tests/utils/test_classes.py
only_utils-0.0.1.dist-info/METADATA
only_utils-0.0.1.dist-info/WHEEL
only_utils-0.0.1.dist-info/top_level.txt
only_utils-0.0.1.dist-info/RECORD
